trainium/__init__.py
trainium-0.1.0.dist-info/licenses/LICENSE
trainium-0.1.0.dist-info/METADATA
trainium-0.1.0.dist-info/WHEEL
trainium-0.1.0.dist-info/top_level.txt
trainium-0.1.0.dist-info/RECORD
