Metadata-Version: 2.4
Name: trainium
Version: 0.1.0
Summary: A Python library that automates your machine learning workflow from data preparation to model deployment
Author-email: anmatngu <nxan2911@gmail.com>
License-Expression: MIT
Requires-Python: >=3.10
License-File: LICENSE
Requires-Dist: joblib>=1.5.0
Requires-Dist: matplotlib>=3.10.3
Requires-Dist: numpy>=2.2.5
Requires-Dist: pandas>=2.2.3
Requires-Dist: psutil>=7.0.0
Requires-Dist: pyyaml>=6.0.2
Requires-Dist: scikit-learn>=1.6.1
Requires-Dist: sqlalchemy>=2.0.41
Requires-Dist: tqdm>=4.67.1
Requires-Dist: types-pyyaml>=6.0.12.20250516
Dynamic: license-file
